Workbook

Sheet Scenarios
A1: Round | B1: Event | C1: Cash % | D1: Bonds % | E1: Shares % | G1: Starting balance | H1: 10000
A2: 1 | B2: A calm year | C2: 2 | D2: 3.5 | E2: 9
A3: 2 | B3: Interest rates jump | C3: 4 | D3: -6 | E3: -3
A4: 3 | B4: Market crash | C4: 3 | D4: 6 | E4: -22
A5: 4 | B5: Recovery rally | C5: 1.5 | D5: 2 | E5: 26
A6: 5 | B6: Inflation creeps in | C6: 3 | D6: -2 | E6: 5

Sheet Checks
A1: Strategy | B1: Round | C1: Cash % | D1: Bonds % | E1: Shares % | F1: Start | G1: Return % | H1: End | I1: Best % | J1: Worst % | K1: Score
A2: Balanced | B2: 1 | C2: 20 | D2: 30 | E2: 50 | F2: =Scenarios!$H$1 -> 10000 | G2: =(C2*INDEX(Scenarios!$C$2:$C$6,B2)+D2*INDEX(Scenarios!$D$2:$D$6,B2)+E2*INDEX(Scenarios!$E$2:$E$6,B2))/100 -> 5.95 | H2: =ROUND(F2*(1+G2/100),2) -> 10595 | I2: =MAX(INDEX(Scenarios!$C$2:$E$6,B2,0)) -> 9 | J2: =MIN(INDEX(Scenarios!$C$2:$E$6,B2,0)) -> 2 | K2: =IF(I2=J2,100,ROUND(100*(G2-J2)/(I2-J2),0)) -> 56
A3: Balanced | B3: 2 | C3: 20 | D3: 30 | E3: 50 | F3: =H2 -> 10595 | G3: =(C3*INDEX(Scenarios!$C$2:$C$6,B3)+D3*INDEX(Scenarios!$D$2:$D$6,B3)+E3*INDEX(Scenarios!$E$2:$E$6,B3))/100 -> -2.5 | H3: =ROUND(F3*(1+G3/100),2) -> 10330.13 | I3: =MAX(INDEX(Scenarios!$C$2:$E$6,B3,0)) -> 4 | J3: =MIN(INDEX(Scenarios!$C$2:$E$6,B3,0)) -> -6 | K3: =IF(I3=J3,100,ROUND(100*(G3-J3)/(I3-J3),0)) -> 35
A4: Balanced | B4: 3 | C4: 20 | D4: 30 | E4: 50 | F4: =H3 -> 10330.13 | G4: =(C4*INDEX(Scenarios!$C$2:$C$6,B4)+D4*INDEX(Scenarios!$D$2:$D$6,B4)+E4*INDEX(Scenarios!$E$2:$E$6,B4))/100 -> -8.6 | H4: =ROUND(F4*(1+G4/100),2) -> 9441.74 | I4: =MAX(INDEX(Scenarios!$C$2:$E$6,B4,0)) -> 6 | J4: =MIN(INDEX(Scenarios!$C$2:$E$6,B4,0)) -> -22 | K4: =IF(I4=J4,100,ROUND(100*(G4-J4)/(I4-J4),0)) -> 48
A5: Balanced | B5: 4 | C5: 20 | D5: 30 | E5: 50 | F5: =H4 -> 9441.74 | G5: =(C5*INDEX(Scenarios!$C$2:$C$6,B5)+D5*INDEX(Scenarios!$D$2:$D$6,B5)+E5*INDEX(Scenarios!$E$2:$E$6,B5))/100 -> 13.9 | H5: =ROUND(F5*(1+G5/100),2) -> 10754.14 | I5: =MAX(INDEX(Scenarios!$C$2:$E$6,B5,0)) -> 26 | J5: =MIN(INDEX(Scenarios!$C$2:$E$6,B5,0)) -> 1.5 | K5: =IF(I5=J5,100,ROUND(100*(G5-J5)/(I5-J5),0)) -> 51
A6: Balanced | B6: 5 | C6: 20 | D6: 30 | E6: 50 | F6: =H5 -> 10754.14 | G6: =(C6*INDEX(Scenarios!$C$2:$C$6,B6)+D6*INDEX(Scenarios!$D$2:$D$6,B6)+E6*INDEX(Scenarios!$E$2:$E$6,B6))/100 -> 2.5 | H6: =ROUND(F6*(1+G6/100),2) -> 11022.99 | I6: =MAX(INDEX(Scenarios!$C$2:$E$6,B6,0)) -> 5 | J6: =MIN(INDEX(Scenarios!$C$2:$E$6,B6,0)) -> -2 | K6: =IF(I6=J6,100,ROUND(100*(G6-J6)/(I6-J6),0)) -> 64
A7: All shares | B7: 1 | C7: 0 | D7: 0 | E7: 100 | F7: =Scenarios!$H$1 -> 10000 | G7: =(C7*INDEX(Scenarios!$C$2:$C$6,B7)+D7*INDEX(Scenarios!$D$2:$D$6,B7)+E7*INDEX(Scenarios!$E$2:$E$6,B7))/100 -> 9 | H7: =ROUND(F7*(1+G7/100),2) -> 10900 | I7: =MAX(INDEX(Scenarios!$C$2:$E$6,B7,0)) -> 9 | J7: =MIN(INDEX(Scenarios!$C$2:$E$6,B7,0)) -> 2 | K7: =IF(I7=J7,100,ROUND(100*(G7-J7)/(I7-J7),0)) -> 100
A8: All shares | B8: 2 | C8: 0 | D8: 0 | E8: 100 | F8: =H7 -> 10900 | G8: =(C8*INDEX(Scenarios!$C$2:$C$6,B8)+D8*INDEX(Scenarios!$D$2:$D$6,B8)+E8*INDEX(Scenarios!$E$2:$E$6,B8))/100 -> -3 | H8: =ROUND(F8*(1+G8/100),2) -> 10573 | I8: =MAX(INDEX(Scenarios!$C$2:$E$6,B8,0)) -> 4 | J8: =MIN(INDEX(Scenarios!$C$2:$E$6,B8,0)) -> -6 | K8: =IF(I8=J8,100,ROUND(100*(G8-J8)/(I8-J8),0)) -> 30
A9: All shares | B9: 3 | C9: 0 | D9: 0 | E9: 100 | F9: =H8 -> 10573 | G9: =(C9*INDEX(Scenarios!$C$2:$C$6,B9)+D9*INDEX(Scenarios!$D$2:$D$6,B9)+E9*INDEX(Scenarios!$E$2:$E$6,B9))/100 -> -22 | H9: =ROUND(F9*(1+G9/100),2) -> 8246.94 | I9: =MAX(INDEX(Scenarios!$C$2:$E$6,B9,0)) -> 6 | J9: =MIN(INDEX(Scenarios!$C$2:$E$6,B9,0)) -> -22 | K9: =IF(I9=J9,100,ROUND(100*(G9-J9)/(I9-J9),0)) -> 0
A10: All shares | B10: 4 | C10: 0 | D10: 0 | E10: 100 | F10: =H9 -> 8246.94 | G10: =(C10*INDEX(Scenarios!$C$2:$C$6,B10)+D10*INDEX(Scenarios!$D$2:$D$6,B10)+E10*INDEX(Scenarios!$E$2:$E$6,B10))/100 -> 26 | H10: =ROUND(F10*(1+G10/100),2) -> 10391.14 | I10: =MAX(INDEX(Scenarios!$C$2:$E$6,B10,0)) -> 26 | J10: =MIN(INDEX(Scenarios!$C$2:$E$6,B10,0)) -> 1.5 | K10: =IF(I10=J10,100,ROUND(100*(G10-J10)/(I10-J10),0)) -> 100
A11: All shares | B11: 5 | C11: 0 | D11: 0 | E11: 100 | F11: =H10 -> 10391.14 | G11: =(C11*INDEX(Scenarios!$C$2:$C$6,B11)+D11*INDEX(Scenarios!$D$2:$D$6,B11)+E11*INDEX(Scenarios!$E$2:$E$6,B11))/100 -> 5 | H11: =ROUND(F11*(1+G11/100),2) -> 10910.7 | I11: =MAX(INDEX(Scenarios!$C$2:$E$6,B11,0)) -> 5 | J11: =MIN(INDEX(Scenarios!$C$2:$E$6,B11,0)) -> -2 | K11: =IF(I11=J11,100,ROUND(100*(G11-J11)/(I11-J11),0)) -> 100
A12: All cash | B12: 1 | C12: 100 | D12: 0 | E12: 0 | F12: =Scenarios!$H$1 -> 10000 | G12: =(C12*INDEX(Scenarios!$C$2:$C$6,B12)+D12*INDEX(Scenarios!$D$2:$D$6,B12)+E12*INDEX(Scenarios!$E$2:$E$6,B12))/100 -> 2 | H12: =ROUND(F12*(1+G12/100),2) -> 10200 | I12: =MAX(INDEX(Scenarios!$C$2:$E$6,B12,0)) -> 9 | J12: =MIN(INDEX(Scenarios!$C$2:$E$6,B12,0)) -> 2 | K12: =IF(I12=J12,100,ROUND(100*(G12-J12)/(I12-J12),0)) -> 0
A13: All cash | B13: 2 | C13: 100 | D13: 0 | E13: 0 | F13: =H12 -> 10200 | G13: =(C13*INDEX(Scenarios!$C$2:$C$6,B13)+D13*INDEX(Scenarios!$D$2:$D$6,B13)+E13*INDEX(Scenarios!$E$2:$E$6,B13))/100 -> 4 | H13: =ROUND(F13*(1+G13/100),2) -> 10608 | I13: =MAX(INDEX(Scenarios!$C$2:$E$6,B13,0)) -> 4 | J13: =MIN(INDEX(Scenarios!$C$2:$E$6,B13,0)) -> -6 | K13: =IF(I13=J13,100,ROUND(100*(G13-J13)/(I13-J13),0)) -> 100
A14: All cash | B14: 3 | C14: 100 | D14: 0 | E14: 0 | F14: =H13 -> 10608 | G14: =(C14*INDEX(Scenarios!$C$2:$C$6,B14)+D14*INDEX(Scenarios!$D$2:$D$6,B14)+E14*INDEX(Scenarios!$E$2:$E$6,B14))/100 -> 3 | H14: =ROUND(F14*(1+G14/100),2) -> 10926.24 | I14: =MAX(INDEX(Scenarios!$C$2:$E$6,B14,0)) -> 6 | J14: =MIN(INDEX(Scenarios!$C$2:$E$6,B14,0)) -> -22 | K14: =IF(I14=J14,100,ROUND(100*(G14-J14)/(I14-J14),0)) -> 89
A15: All cash | B15: 4 | C15: 100 | D15: 0 | E15: 0 | F15: =H14 -> 10926.24 | G15: =(C15*INDEX(Scenarios!$C$2:$C$6,B15)+D15*INDEX(Scenarios!$D$2:$D$6,B15)+E15*INDEX(Scenarios!$E$2:$E$6,B15))/100 -> 1.5 | H15: =ROUND(F15*(1+G15/100),2) -> 11090.13 | I15: =MAX(INDEX(Scenarios!$C$2:$E$6,B15,0)) -> 26 | J15: =MIN(INDEX(Scenarios!$C$2:$E$6,B15,0)) -> 1.5 | K15: =IF(I15=J15,100,ROUND(100*(G15-J15)/(I15-J15),0)) -> 0
A16: All cash | B16: 5 | C16: 100 | D16: 0 | E16: 0 | F16: =H15 -> 11090.13 | G16: =(C16*INDEX(Scenarios!$C$2:$C$6,B16)+D16*INDEX(Scenarios!$D$2:$D$6,B16)+E16*INDEX(Scenarios!$E$2:$E$6,B16))/100 -> 3 | H16: =ROUND(F16*(1+G16/100),2) -> 11422.83 | I16: =MAX(INDEX(Scenarios!$C$2:$E$6,B16,0)) -> 5 | J16: =MIN(INDEX(Scenarios!$C$2:$E$6,B16,0)) -> -2 | K16: =IF(I16=J16,100,ROUND(100*(G16-J16)/(I16-J16),0)) -> 71
A17: Switcher | B17: 1 | C17: 10 | D17: 20 | E17: 70 | F17: =Scenarios!$H$1 -> 10000 | G17: =(C17*INDEX(Scenarios!$C$2:$C$6,B17)+D17*INDEX(Scenarios!$D$2:$D$6,B17)+E17*INDEX(Scenarios!$E$2:$E$6,B17))/100 -> 7.2 | H17: =ROUND(F17*(1+G17/100),2) -> 10720 | I17: =MAX(INDEX(Scenarios!$C$2:$E$6,B17,0)) -> 9 | J17: =MIN(INDEX(Scenarios!$C$2:$E$6,B17,0)) -> 2 | K17: =IF(I17=J17,100,ROUND(100*(G17-J17)/(I17-J17),0)) -> 74
A18: Switcher | B18: 2 | C18: 70 | D18: 20 | E18: 10 | F18: =H17 -> 10720 | G18: =(C18*INDEX(Scenarios!$C$2:$C$6,B18)+D18*INDEX(Scenarios!$D$2:$D$6,B18)+E18*INDEX(Scenarios!$E$2:$E$6,B18))/100 -> 1.3 | H18: =ROUND(F18*(1+G18/100),2) -> 10859.36 | I18: =MAX(INDEX(Scenarios!$C$2:$E$6,B18,0)) -> 4 | J18: =MIN(INDEX(Scenarios!$C$2:$E$6,B18,0)) -> -6 | K18: =IF(I18=J18,100,ROUND(100*(G18-J18)/(I18-J18),0)) -> 73
A19: Switcher | B19: 3 | C19: 15 | D19: 70 | E19: 15 | F19: =H18 -> 10859.36 | G19: =(C19*INDEX(Scenarios!$C$2:$C$6,B19)+D19*INDEX(Scenarios!$D$2:$D$6,B19)+E19*INDEX(Scenarios!$E$2:$E$6,B19))/100 -> 1.35 | H19: =ROUND(F19*(1+G19/100),2) -> 11005.96 | I19: =MAX(INDEX(Scenarios!$C$2:$E$6,B19,0)) -> 6 | J19: =MIN(INDEX(Scenarios!$C$2:$E$6,B19,0)) -> -22 | K19: =IF(I19=J19,100,ROUND(100*(G19-J19)/(I19-J19),0)) -> 83
A20: Switcher | B20: 4 | C20: 0 | D20: 5 | E20: 95 | F20: =H19 -> 11005.96 | G20: =(C20*INDEX(Scenarios!$C$2:$C$6,B20)+D20*INDEX(Scenarios!$D$2:$D$6,B20)+E20*INDEX(Scenarios!$E$2:$E$6,B20))/100 -> 24.8 | H20: =ROUND(F20*(1+G20/100),2) -> 13735.44 | I20: =MAX(INDEX(Scenarios!$C$2:$E$6,B20,0)) -> 26 | J20: =MIN(INDEX(Scenarios!$C$2:$E$6,B20,0)) -> 1.5 | K20: =IF(I20=J20,100,ROUND(100*(G20-J20)/(I20-J20),0)) -> 95
A21: Switcher | B21: 5 | C21: 45 | D21: 10 | E21: 45 | F21: =H20 -> 13735.44 | G21: =(C21*INDEX(Scenarios!$C$2:$C$6,B21)+D21*INDEX(Scenarios!$D$2:$D$6,B21)+E21*INDEX(Scenarios!$E$2:$E$6,B21))/100 -> 3.4 | H21: =ROUND(F21*(1+G21/100),2) -> 14202.44 | I21: =MAX(INDEX(Scenarios!$C$2:$E$6,B21,0)) -> 5 | J21: =MIN(INDEX(Scenarios!$C$2:$E$6,B21,0)) -> -2 | K21: =IF(I21=J21,100,ROUND(100*(G21-J21)/(I21-J21),0)) -> 77
